Spec7DT/__init__.py
Spec7DT/division/__init__.py
Spec7DT/division/binning.py
Spec7DT/division/cutout.py
Spec7DT/handlers/__init__.py
Spec7DT/handlers/_legacy_filter_handler.py
Spec7DT/handlers/filter_handler.py
Spec7DT/manipulation/__init__.py
Spec7DT/manipulation/mask.py
Spec7DT/manipulation/reddening.py
Spec7DT/manipulation/sky_interpolate.py
Spec7DT/plot/__init__.py
Spec7DT/plot/plot.py
Spec7DT/reduction/PSF.py
Spec7DT/reduction/__init__.py
Spec7DT/reduction/background.py
Spec7DT/reference/filter_curves/2MASS.H.dat
Spec7DT/reference/filter_curves/2MASS.J.dat
Spec7DT/reference/filter_curves/2MASS.Ks.dat
Spec7DT/reference/filter_curves/7DT.m400.dat
Spec7DT/reference/filter_curves/7DT.m425.dat
Spec7DT/reference/filter_curves/7DT.m450.dat
Spec7DT/reference/filter_curves/7DT.m475.dat
Spec7DT/reference/filter_curves/7DT.m500.dat
Spec7DT/reference/filter_curves/7DT.m525.dat
Spec7DT/reference/filter_curves/7DT.m550.dat
Spec7DT/reference/filter_curves/7DT.m575.dat
Spec7DT/reference/filter_curves/7DT.m600.dat
Spec7DT/reference/filter_curves/7DT.m625.dat
Spec7DT/reference/filter_curves/7DT.m650.dat
Spec7DT/reference/filter_curves/7DT.m675.dat
Spec7DT/reference/filter_curves/7DT.m700.dat
Spec7DT/reference/filter_curves/7DT.m725.dat
Spec7DT/reference/filter_curves/7DT.m750.dat
Spec7DT/reference/filter_curves/7DT.m775.dat
Spec7DT/reference/filter_curves/7DT.m800.dat
Spec7DT/reference/filter_curves/7DT.m825.dat
Spec7DT/reference/filter_curves/7DT.m850.dat
Spec7DT/reference/filter_curves/7DT.m875.dat
Spec7DT/reference/filter_curves/GALEX.NUV.dat
Spec7DT/reference/filter_curves/PS1.g.dat
Spec7DT/reference/filter_curves/PS1.i.dat
Spec7DT/reference/filter_curves/PS1.r.dat
Spec7DT/reference/filter_curves/PS1.y.dat
Spec7DT/reference/filter_curves/PS1.z.dat
Spec7DT/reference/filter_curves/SDSS.g.dat
Spec7DT/reference/filter_curves/SDSS.i.dat
Spec7DT/reference/filter_curves/SDSS.r.dat
Spec7DT/reference/filter_curves/SDSS.u.dat
Spec7DT/reference/filter_curves/SDSS.z.dat
spec7dt-0.11.0.dist-info/METADATA
spec7dt-0.11.0.dist-info/WHEEL
spec7dt-0.11.0.dist-info/top_level.txt
spec7dt-0.11.0.dist-info/RECORD
