Metadata-Version: 2.4
Name: Spec7DT
Version: 0.11.0
Summary: Spectral image handling package for 7-Dimensional Telescope users by Won-Hyeong Lee
Home-page: https://github.com/Yicircle/Spec7DT
Author: Won-Hyeong Lee
Author-email: wohy1220@gmail.com
Classifier: Programming Language :: Python :: 3.10
Classifier: Programming Language :: Python :: 3.11
Classifier: Programming Language :: Python :: 3.12
Requires-Python: >=3.10
Requires-Dist: numpy
Requires-Dist: astropy
Requires-Dist: matplotlib
Requires-Dist: seaborn
Requires-Dist: pathlib
Requires-Dist: photutils
Requires-Dist: reproject
Dynamic: author
Dynamic: author-email
Dynamic: classifier
Dynamic: home-page
Dynamic: keywords
Dynamic: requires-dist
Dynamic: requires-python
Dynamic: summary
